create_django_app_irwin/__init__.py
create_django_app_irwin/cli.py
create_django_app_irwin-0.0.12.dist-info/licenses/LICENSE
create_django_app_irwin-0.0.12.dist-info/METADATA
create_django_app_irwin-0.0.12.dist-info/WHEEL
create_django_app_irwin-0.0.12.dist-info/entry_points.txt
create_django_app_irwin-0.0.12.dist-info/top_level.txt
create_django_app_irwin-0.0.12.dist-info/RECORD
