Metadata-Version: 2.4
Name: create_django_app_irwin
Version: 0.0.12
Summary: Génère une structure d’app Django automatiquement
Author: DJRIGA IRWIN JESSY
Author-email: irwindjriga@gmail.com
License: MIT
Classifier: Programming Language :: Python :: 3
Classifier: Operating System :: OS Independent
Requires-Python: >=3.6
License-File: LICENSE
Dynamic: author
Dynamic: author-email
Dynamic: classifier
Dynamic: description
Dynamic: description-content-type
Dynamic: license
Dynamic: license-file
Dynamic: requires-python
Dynamic: summary
